symbol_catbuffer/AccountAddressRestrictionTransactionBodyBuilder.py
symbol_catbuffer/AccountAddressRestrictionTransactionBuilder.py
symbol_catbuffer/AccountKeyLinkTransactionBodyBuilder.py
symbol_catbuffer/AccountKeyLinkTransactionBuilder.py
symbol_catbuffer/AccountKeyTypeFlagsDto.py
symbol_catbuffer/AccountMetadataTransactionBodyBuilder.py
symbol_catbuffer/AccountMetadataTransactionBuilder.py
symbol_catbuffer/AccountMosaicRestrictionTransactionBodyBuilder.py
symbol_catbuffer/AccountMosaicRestrictionTransactionBuilder.py
symbol_catbuffer/AccountOperationRestrictionTransactionBodyBuilder.py
symbol_catbuffer/AccountOperationRestrictionTransactionBuilder.py
symbol_catbuffer/AccountRestrictionAddressValueBuilder.py
symbol_catbuffer/AccountRestrictionFlagsDto.py
symbol_catbuffer/AccountRestrictionMosaicValueBuilder.py
symbol_catbuffer/AccountRestrictionTransactionTypeValueBuilder.py
symbol_catbuffer/AccountRestrictionsBuilder.py
symbol_catbuffer/AccountRestrictionsInfoBuilder.py
symbol_catbuffer/AccountStateBuilder.py
symbol_catbuffer/AccountStateFormatDto.py
symbol_catbuffer/AccountTypeDto.py
symbol_catbuffer/AddressAliasTransactionBodyBuilder.py
symbol_catbuffer/AddressAliasTransactionBuilder.py
symbol_catbuffer/AddressDto.py
symbol_catbuffer/AddressKeyValueBuilder.py
symbol_catbuffer/AddressKeyValueSetBuilder.py
symbol_catbuffer/AddressResolutionEntryBuilder.py
symbol_catbuffer/AddressResolutionStatementBuilder.py
symbol_catbuffer/AggregateBondedTransactionBuilder.py
symbol_catbuffer/AggregateCompleteTransactionBuilder.py
symbol_catbuffer/AggregateTransactionBodyBuilder.py
symbol_catbuffer/AliasActionDto.py
symbol_catbuffer/AmountDto.py
symbol_catbuffer/BalanceChangeReceiptBuilder.py
symbol_catbuffer/BalanceTransferReceiptBuilder.py
symbol_catbuffer/BlockDurationDto.py
symbol_catbuffer/BlockFeeMultiplierDto.py
symbol_catbuffer/BlockHeaderBuilder.py
symbol_catbuffer/CosignatureBuilder.py
symbol_catbuffer/DetachedCosignatureBuilder.py
symbol_catbuffer/DifficultyDto.py
catbuffer-1.0.0.dist-info/LICENSE
catbuffer-1.0.0.dist-info/METADATA
catbuffer-1.0.0.dist-info/WHEEL
catbuffer-1.0.0.dist-info/top_level.txt
catbuffer-1.0.0.dist-info/RECORD
