Metadata-Version: 2.1
Name: catbuffer
Version: 1.0.0
Summary: Symbol Catbuffer Builders
Home-page: https://github.com/nemtech/catbuffer-generators
Author: NEM Group
Author-email: dev@nem.software
License: Apache 2.0
Keywords: catbuffer-generators,catbuffer,builders,Symbol Catbuffer Builders
Platform: UNKNOWN
Classifier: Programming Language :: Python :: 3.7
